utinypass/__init__.py
utinypass/client.py
utinypass/crypto.py
utinypass-0.2.2.dist-info/DESCRIPTION.rst
utinypass-0.2.2.dist-info/METADATA
utinypass-0.2.2.dist-info/metadata.json
utinypass-0.2.2.dist-info/RECORD
utinypass-0.2.2.dist-info/top_level.txt
utinypass-0.2.2.dist-info/WHEEL
