Metadata-Version: 2.0
Name: utinypass
Version: 0.2.2
Summary: UNOFFICIAL TinyPass utility library.
Home-page: http://github.com/gfranxman/utinypass/
Author: Glenn Franxman
Author-email: gfranxman@gmail.com
License: MIT
Platform: UNKNOWN
Classifier: Development Status :: 3 - Alpha
Classifier: Intended Audience :: Developers
Classifier: Natural Language :: English
Classifier: License :: OSI Approved :: MIT License
Classifier: Operating System :: OS Independent
Classifier: Programming Language :: Python
Classifier: Programming Language :: Python :: 2
Classifier: Programming Language :: Python :: 2.6
Classifier: Programming Language :: Python :: 2.7
Classifier: Programming Language :: Python :: 3
Classifier: Programming Language :: Python :: 3.3
Classifier: Topic :: Software Development :: Libraries :: Python Modules
Requires-Dist: pprp
Requires-Dist: requests
